roolink/__init__.py
roolink/client.py
roolink/types/__init__.py
roolink/types/bmp.py
roolink/types/web.py
roolink-1.0.4.dist-info/licenses/LICENSE
roolink-1.0.4.dist-info/METADATA
roolink-1.0.4.dist-info/WHEEL
roolink-1.0.4.dist-info/top_level.txt
roolink-1.0.4.dist-info/RECORD
