Metadata-Version: 2.4
Name: roolink
Version: 1.0.4
Summary: Official Roolink SDK for Python
Author: Roolink
License: MIT
Project-URL: Homepage, https://github.com/roolinkio/roolink-py
Project-URL: Documentation, https://docs.roolink.io
Project-URL: Source Code, https://github.com/roolinkio/roolink-py
Project-URL: Bug Tracker, https://github.com/roolinkio/roolink-py/issues
Keywords: roolink,akamai,sensor,sdk
Classifier: Development Status :: 5 - Production/Stable
Classifier: Intended Audience :: Developers
Classifier: License :: OSI Approved :: MIT License
Classifier: Programming Language :: Python :: 3
Classifier: Programming Language :: Python :: 3.8
Classifier: Programming Language :: Python :: 3.9
Classifier: Programming Language :: Python :: 3.10
Classifier: Programming Language :: Python :: 3.11
Classifier: Programming Language :: Python :: 3.12
Requires-Python: >=3.8
License-File: LICENSE
Requires-Dist: httpx[http2]>=0.27.0
Dynamic: license-file
